{
    "Ar36": {
        "error": 0.00018203483579769578, 
        "fit": "previous", 
        "references": [
            {
                "exclude": false, 
                "record_id": "bu-FC-J-7435"
            }
        ], 
        "value": 0.004714388500517675
    }, 
    "Ar37": {
        "error": 0.005239527915870326, 
        "fit": "previous", 
        "references": [
            {
                "exclude": false, 
                "record_id": "bu-FC-J-7435"
            }
        ], 
        "value": 0.03834244675138555
    }, 
    "Ar38": {
        "error": 0.0021226974725412676, 
        "fit": "previous", 
        "references": [
            {
                "exclude": false, 
                "record_id": "bu-FC-J-7435"
            }
        ], 
        "value": 0.0056711727742193505
    }, 
    "Ar39": {
        "error": 0.008969855811891735, 
        "fit": "previous", 
        "references": [
            {
                "exclude": false, 
                "record_id": "bu-FC-J-7435"
            }
        ], 
        "value": 0.031928720124102514
    }, 
    "Ar40": {
        "error": 0.006891007377644617, 
        "fit": "previous", 
        "references": [
            {
                "exclude": false, 
                "record_id": "bu-FC-J-7435"
            }
        ], 
        "value": 0.380388308479536
    }, 
    "PM41": {
        "error": 0.06742466717200439, 
        "fit": "previous", 
        "references": [
            {
                "exclude": false, 
                "record_id": "bu-FC-J-7435"
            }
        ], 
        "value": 0.03194284533714303
    }
}