{
    "AX": {
        "error": 0.008091086984525911,
        "error_type": "SEM",
        "filter_outliers_dict": {
            "filter_outliers": true,
            "iterations": 1,
            "std_devs": 3,
            "use_iqr_filtering": false,
            "use_standard_deviation_filtering": false
        },
        "fit": "average",
        "fn": 35,
        "include_baseline_error": false,
        "modifier_error": 0.0,
        "modifier_value": 0.0,
        "n": 35,
        "outlier_excluded": [],
        "reviewed": true,
        "user_excluded": [],
        "value": 0.05060280009305903
    },
    "CDD": {
        "error": 1.139149979245107e-05,
        "error_type": "SEM",
        "filter_outliers_dict": {
            "filter_outliers": true,
            "iterations": 1,
            "std_devs": 10,
            "use_iqr_filtering": false,
            "use_standard_deviation_filtering": false
        },
        "fit": "average",
        "fn": 35,
        "include_baseline_error": false,
        "modifier_error": 3.172252386287065e-05,
        "modifier_value": 0.00022740457692646288,
        "n": 35,
        "outlier_excluded": [],
        "reviewed": true,
        "user_excluded": [],
        "value": 0.0002497958692921592
    },
    "H1": {
        "error": 0.0074329071812377166,
        "error_type": "SEM",
        "filter_outliers_dict": {
            "filter_outliers": true,
            "iterations": 1,
            "std_devs": 3,
            "use_iqr_filtering": false,
            "use_standard_deviation_filtering": false
        },
        "fit": "average",
        "fn": 35,
        "include_baseline_error": false,
        "modifier_error": 0.0,
        "modifier_value": 0.0,
        "n": 35,
        "outlier_excluded": [],
        "reviewed": true,
        "user_excluded": [],
        "value": 0.010405804509563105
    },
    "H2": {
        "error": 0.008259835061648737,
        "error_type": "SEM",
        "filter_outliers_dict": {
            "filter_outliers": true,
            "iterations": 1,
            "std_devs": 2
        },
        "fit": "average",
        "modifier_error": 0.0,
        "modifier_value": 0.0,
        "value": 0.014764359148457291
    },
    "L1": {
        "error": 0.004979487536527237,
        "error_type": "SEM",
        "filter_outliers_dict": {
            "filter_outliers": true,
            "iterations": 1,
            "std_devs": 3,
            "use_iqr_filtering": false,
            "use_standard_deviation_filtering": false
        },
        "fit": "average",
        "fn": 34,
        "include_baseline_error": false,
        "modifier_error": 0.0,
        "modifier_value": 0.0,
        "n": 35,
        "outlier_excluded": [
            17
        ],
        "reviewed": true,
        "user_excluded": [],
        "value": 0.04134502828203361
    },
    "L2": {
        "error": 0.004784084754433137,
        "error_type": "SEM",
        "filter_outliers_dict": {
            "filter_outliers": true,
            "iterations": 1,
            "std_devs": 3,
            "use_iqr_filtering": false,
            "use_standard_deviation_filtering": false
        },
        "fit": "average",
        "fn": 35,
        "include_baseline_error": false,
        "modifier_error": 0.0,
        "modifier_value": 0.0,
        "n": 35,
        "outlier_excluded": [],
        "reviewed": true,
        "user_excluded": [],
        "value": -0.04291807726757335
    }
}