{
    "Ar36": {
        "error": 0.00011766345050032991,
        "error_type": "",
        "fit": "previous",
        "references": [
            {
                "exclude": false,
                "record_id": "bu-FD-F-3087"
            }
        ],
        "value": 0.0030024333950603808
    },
    "Ar37": {
        "error": 0.005500171527556231,
        "error_type": "",
        "fit": "previous",
        "references": [
            {
                "exclude": false,
                "record_id": "bu-FD-F-3087"
            }
        ],
        "value": 0.020488038158581957
    },
    "Ar38": {
        "error": 0.09484778805176933,
        "error_type": "",
        "fit": "previous",
        "references": [
            {
                "exclude": false,
                "record_id": "bu-FD-F-3087"
            }
        ],
        "value": -0.22528477590150842
    },
    "Ar39": {
        "error": 0.00709971587883049,
        "error_type": "",
        "fit": "previous",
        "references": [
            {
                "exclude": false,
                "record_id": "bu-FD-F-3087"
            }
        ],
        "value": 0.028606060879293273
    },
    "Ar40": {
        "error": 0.012814427679925619,
        "error_type": "",
        "fit": "previous",
        "references": [
            {
                "exclude": false,
                "record_id": "bu-FD-F-3087"
            }
        ],
        "value": 1.369726110734411
    }
}