{
    "AX": {
        "error": 0.009983660096738326,
        "error_type": "SEM",
        "filter_outliers_dict": {
            "filter_outliers": true,
            "iterations": 1,
            "std_devs": 3,
            "use_iqr_filtering": false,
            "use_standard_deviation_filtering": false
        },
        "fit": "average",
        "fn": 35,
        "include_baseline_error": false,
        "modifier_error": 0.0,
        "modifier_value": 0.0,
        "n": 35,
        "outlier_excluded": [],
        "reviewed": true,
        "user_excluded": [],
        "value": 0.04398731803854129
    },
    "CDD": {
        "error": 6.553703860833149e-06,
        "error_type": "SEM",
        "filter_outliers_dict": {
            "filter_outliers": true,
            "iterations": 1,
            "std_devs": 10,
            "use_iqr_filtering": false,
            "use_standard_deviation_filtering": false
        },
        "fit": "average",
        "fn": 35,
        "include_baseline_error": false,
        "modifier_error": 1.499055859171326e-05,
        "modifier_value": 5.077376156525e-05,
        "n": 35,
        "outlier_excluded": [],
        "reviewed": true,
        "user_excluded": [],
        "value": 6.018147864129527e-05
    },
    "H1": {
        "error": 0.00757277548430442,
        "error_type": "SEM",
        "filter_outliers_dict": {
            "filter_outliers": true,
            "iterations": 1,
            "std_devs": 3,
            "use_iqr_filtering": false,
            "use_standard_deviation_filtering": false
        },
        "fit": "average",
        "fn": 35,
        "include_baseline_error": false,
        "modifier_error": 0.0,
        "modifier_value": 0.0,
        "n": 35,
        "outlier_excluded": [],
        "reviewed": true,
        "user_excluded": [],
        "value": -0.2746421707527978
    },
    "H2": {
        "error": 0.005400925514178729,
        "error_type": "SEM",
        "filter_outliers_dict": {
            "filter_outliers": true,
            "iterations": 1,
            "std_devs": 3,
            "use_iqr_filtering": false,
            "use_standard_deviation_filtering": false
        },
        "fit": "average",
        "fn": 35,
        "include_baseline_error": false,
        "modifier_error": 0.0,
        "modifier_value": 0.0,
        "n": 35,
        "outlier_excluded": [],
        "reviewed": true,
        "user_excluded": [],
        "value": 0.10383378001196043
    },
    "L1": {
        "error": 0.0043178190818769545,
        "error_type": "SEM",
        "filter_outliers_dict": {
            "filter_outliers": true,
            "iterations": 1,
            "std_devs": 3,
            "use_iqr_filtering": false,
            "use_standard_deviation_filtering": false
        },
        "fit": "average",
        "fn": 35,
        "include_baseline_error": false,
        "modifier_error": 0.0,
        "modifier_value": 0.0,
        "n": 35,
        "outlier_excluded": [],
        "reviewed": true,
        "user_excluded": [],
        "value": 0.03877846793537693
    },
    "L2": {
        "error": 0.005017204439501684,
        "error_type": "SEM",
        "filter_outliers_dict": {
            "filter_outliers": true,
            "iterations": 1,
            "std_devs": 3,
            "use_iqr_filtering": false,
            "use_standard_deviation_filtering": false
        },
        "fit": "average",
        "fn": 35,
        "include_baseline_error": false,
        "modifier_error": 0.0,
        "modifier_value": 0.0,
        "n": 35,
        "outlier_excluded": [],
        "reviewed": true,
        "user_excluded": [],
        "value": -0.02399104449099728
    }
}